openai_realtime_client/__init__.py
openai_realtime_client/client/__init__.py
openai_realtime_client/client/realtime_client.py
openai_realtime_client/handlers/__init__.py
openai_realtime_client/handlers/audio_handler.py
openai_realtime_client/handlers/input_handler.py
openai_realtime_client-0.1.0.dist-info/METADATA
openai_realtime_client-0.1.0.dist-info/WHEEL
openai_realtime_client-0.1.0.dist-info/RECORD
