Metadata-Version: 2.1
Name: openai-realtime-client
Version: 0.1.0
Summary: A python-based client for OpenAI's Realtime API
License: MIT
Author: Logan Markewich
Author-email: logan@runllama.ai
Requires-Python: >=3.10,<4.0
Classifier: License :: OSI Approved :: MIT License
Classifier: Programming Language :: Python :: 3
Classifier: Programming Language :: Python :: 3.10
Classifier: Programming Language :: Python :: 3.11
Classifier: Programming Language :: Python :: 3.12
Requires-Dist: llama-index-core (>=0.11.17,<0.12.0)
Requires-Dist: pyaudio (>=0.2.14,<0.3.0)
Requires-Dist: pydub (>=0.25.1,<0.26.0)
Requires-Dist: pynput (>=1.7.7,<2.0.0)
Requires-Dist: wave (>=0.0.2,<0.0.3)
Requires-Dist: websockets (>=13.1,<14.0)
